LICENSE
MANIFEST.in
setup.cfg
setup.py
asptest/__init__.py
asptest/classes.py
asptest/commons.py
asptest/hooks.py
asptest/parsers.py
asptest/plugin.py
pytest_asptest.egg-info/PKG-INFO
pytest_asptest.egg-info/SOURCES.txt
pytest_asptest.egg-info/dependency_links.txt
pytest_asptest.egg-info/entry_points.txt
pytest_asptest.egg-info/not-zip-safe
pytest_asptest.egg-info/requires.txt
pytest_asptest.egg-info/top_level.txt
test/test_asptest.py