Metadata-Version: 1.1
Name: pytest-asptest
Version: 0.1.0
Summary: test Answer Set Programming programs
Home-page: https://github.com/aluriak/pytest-asptest
Author: Lucas Bourneuf
Author-email: lucas.bourneuf@laposte.net
License: MIT
Platform: UNKNOWN
Classifier: Development Status :: 4 - Beta
Classifier: Framework :: Pytest
Classifier: Intended Audience :: Developers
Classifier: Topic :: Software Development :: Testing
Classifier: Programming Language :: Python
Classifier: Programming Language :: Python :: 3
Classifier: Programming Language :: Python :: 3.4
Classifier: Programming Language :: Python :: Implementation :: CPython
Classifier: Operating System :: OS Independent
Classifier: License :: OSI Approved :: MIT License
